pyjano/__init__.py
pyjano/jana/__init__.py
pyjano/jana/generator.py
pyjano/jana/jana.py
pyjano/jana/mini_plugin_generator.py
pyjano/jana/plugin.py
pyjano/notebook_extension.py
pyjano/plot/__init__.py
pyjano/plot/test.py
pyjano/plugin_parser/__init__.py
pyjano/plugin_parser/prepared.py
pyjano/server/.gitignore
pyjano/server/README.md
pyjano/server/__init__.py
pyjano/server/jana.py
pyjano/server/run_downloader.py
pyjano/server/run_server.py
pyjano/server/socket/__init__.py.old
pyjano/server/socket/events.py
pyjano/server/socket/forms.py
pyjano/server/socket/routes.py
pyjano/server/static/logo_large.jpg
pyjano/server/static/plugins.css
pyjano/server/static/plugins.js
pyjano/server/templates/chat.html
pyjano/server/templates/index.html
pyjano/server/templates/jana.html
pyjano/server/templates/layout_full.html
pyjano/server/templates/layout_short.html
pyjano/server/templates/plugins.html
pyjano/server/templates/start.html
pyjano/version.py
pyjano-1.1.0.dist-info/METADATA
pyjano-1.1.0.dist-info/WHEEL
pyjano-1.1.0.dist-info/LICENSE
pyjano-1.1.0.dist-info/RECORD
